LICENSE
MANIFEST.in
README.rst
setup.py
src/oppa/__init__.py
src/oppa/gui.py
src/oppa/main.py
src/oppa/state.py
src/oppa.egg-info/PKG-INFO
src/oppa.egg-info/SOURCES.txt
src/oppa.egg-info/dependency_links.txt
src/oppa.egg-info/entry_points.txt
src/oppa.egg-info/top_level.txt