Metadata-Version: 1.1
Name: oppa
Version: 0.5.0
Summary: Presentation and lecture support tool
Home-page: https://github.com/lkrotowski/oppa
Author: Łukasz Krotowski
Author-email: lukasz.krotowski@gmail.com
License: GPLv3
Platform: UNKNOWN
Classifier: Development Status :: 4 - Beta
Classifier: Environment :: Win32 (MS Windows)
Classifier: Environment :: X11 Applications :: GTK
Classifier: License :: OSI Approved :: GNU General Public License v3 (GPLv3)
Classifier: Operating System :: Microsoft :: Windows
Classifier: Operating System :: POSIX :: Linux
Classifier: Topic :: Education :: Computer Aided Instruction (CAI)
Classifier: Topic :: Multimedia :: Graphics :: Presentation
